<?xml version="1.0" encoding="UTF-8"?>
<beans profile="emc" xmlns="http://www.springframework.org/schema/beans"
       xmlns:xsi="http://www.w3.org/2001/XMLSchema-instance"
       xsi:schemaLocation="http://www.springframework.org/schema/beans  http://www.springframework.org/schema/beans/spring-beans-3.1.xsd">

    <import resource="classpath:security-ciphers.xml" />

    <bean id="signAlgo" class="org.springframework.beans.factory.config.MethodInvokingFactoryBean">
        <property name="targetClass"
                  value="com.emc.storageos.security.keystore.impl.KeyCertificateAlgorithmValuesHolder"/>
        <property name="targetMethod" value="setSigningAlgorithm"/>
        <property name="arguments" value="SHA256withRSA"/>
    </bean>

    <bean id="randomAlgo" class="org.springframework.beans.factory.config.MethodInvokingFactoryBean">
        <property name="targetClass" value="com.emc.storageos.security.helpers.SecurityUtil"/>
        <property name="targetMethod" value="setSecuredRandomAlgorithm"/>
        <property name="arguments" value="HMACDRBG256"/>
    </bean>

    <bean id="securityService" class="com.emc.storageos.security.helpers.proprietary.SecurityServiceJSafe">
        <property name="ciphers" ref="strongCiphers"/>
    </bean>

    <bean id="securityUtil" class="org.springframework.beans.factory.config.MethodInvokingFactoryBean">
        <property name="targetClass" value="com.emc.storageos.security.helpers.SecurityUtil"/>
        <property name="targetMethod" value="setSecurityService"/>
        <property name="arguments" ref="securityService"/>
    </bean>

    <bean id="initProvider" class="org.springframework.beans.factory.config.MethodInvokingFactoryBean">
        <property name="targetClass" value="com.emc.storageos.security.helpers.SecurityUtil"/>
        <property name="targetMethod" value="initSecurityProvider"/>
    </bean>
</beans>
